README
setup.py
Jynx.egg-info/PKG-INFO
Jynx.egg-info/SOURCES.txt
Jynx.egg-info/dependency_links.txt
Jynx.egg-info/top_level.txt
jynx/__init__.py
jynx/jannotations.py
jynx/jclasspath.py
jynx/jcompile.py
jynx/sentinel.py
jynx/lib/__init__.py
jynx/lib/hibernate/__init__.py
jynx/lib/hibernate/annotations.py
jynx/lib/hibernate/config.py
jynx/lib/hibernate/contextmanager.py
jynx/lib/hibernate/sessionfactory.py
jynx/lib/hibernate/tests/__init__.py
jynx/lib/hibernate/tests/derby_session.py
jynx/lib/hibernate/tests/test_anno_ext.py
jynx/lib/hibernate/tests/test_embedded.py
jynx/lib/hibernate/tests/test_join.py
jynx/lib/hibernate/tests/test_one2one.py
jynx/lib/javaparser/__init__.py
jynx/lib/javaparser/tests/__init__.py
jynx/lib/javaparser/tests/test_javaparser.py
jynx/lib/junit/__init__.py
jynx/lib/util/__init__.py
jynx/lib/util/chooser.py
jynx/lib/util/reverb.py
jynx/lib/util/table.py
jynx/tests/__init__.py
jynx/tests/test_jannotations.py
jynx/tests/test_jcompile.py
jynx/tests/test_junit.py
org/javaparser/COPYING
org/javaparser/COPYING.LESSER
org/javaparser/TypeVisitor.class
org/javaparser/TypeVisitor.java
org/javaparser/javaparser-1.0.7.jar
org/javaparser/readme.txt
org/junit/junit-4.6.jar
org/jynx/JyGateway.class
org/jynx/JyGateway.java
org/jynx/gen/README
org/jynx/gen/Sentinel.class
org/jynx/gen/Sentinel.java
org/slf4j/slf4j-api-1.5.8.jar
org/slf4j/slf4j-nop-1.5.8.jar
org/slf4j/slf4j-simple-1.5.8.jar