Metadata-Version: 1.1
Name: Jynx
Version: 0.4.2-jython
Summary: Jython library for Python integration with modern Java using dynamic Java compilation
Home-page: http://www.fiber-space.de/
Author: Kay Schluehr
Author-email: kay@fiber-space.de
License: MIT License
Download-URL: http://code.google.com/p/jynx/
Platform: UNKNOWN
